apimaticcalculatorlatest/__init__.py
apimaticcalculatorlatest/api_helper.py
apimaticcalculatorlatest/apimaticcalculatorlatest_client.py
apimaticcalculatorlatest/configuration.py
apimaticcalculatorlatest/decorators.py
apimaticcalculatorlatest/controllers/__init__.py
apimaticcalculatorlatest/controllers/authorization_controller.py
apimaticcalculatorlatest/controllers/base_controller.py
apimaticcalculatorlatest/controllers/fee_and_tax_controller.py
apimaticcalculatorlatest/controllers/fee_and_tax_mandatory_at_the_property_level_controller.py
apimaticcalculatorlatest/controllers/images_controller.py
apimaticcalculatorlatest/controllers/los_pricing_controller.py
apimaticcalculatorlatest/controllers/messaging_controller.py
apimaticcalculatorlatest/controllers/product_controller.py
apimaticcalculatorlatest/controllers/property_managers_controller.py
apimaticcalculatorlatest/controllers/push_notification_controller.py
apimaticcalculatorlatest/controllers/rates_and_availability_controller.py
apimaticcalculatorlatest/controllers/request_to_book_controller.py
apimaticcalculatorlatest/controllers/reservation_notifications_controller.py
apimaticcalculatorlatest/controllers/testing_of_message_api_calls_controller.py
apimaticcalculatorlatest/controllers/validation_controller.py
apimaticcalculatorlatest/controllers/yields_controller.py
apimaticcalculatorlatest/exceptions/__init__.py
apimaticcalculatorlatest/exceptions/api_exception.py
apimaticcalculatorlatest/http/__init__.py
apimaticcalculatorlatest/http/http_call_back.py
apimaticcalculatorlatest/http/http_client.py
apimaticcalculatorlatest/http/http_context.py
apimaticcalculatorlatest/http/http_method_enum.py
apimaticcalculatorlatest/http/http_request.py
apimaticcalculatorlatest/http/http_response.py
apimaticcalculatorlatest/http/requests_client.py
apimaticcalculatorlatest/http/auth/__init__.py
apimaticcalculatorlatest/http/auth/custom_query_auth.py
apimaticcalculatorlatest/models/__init__.py
apimaticcalculatorlatest-4.0.0.dist-info/LICENSE
apimaticcalculatorlatest-4.0.0.dist-info/METADATA
apimaticcalculatorlatest-4.0.0.dist-info/WHEEL
apimaticcalculatorlatest-4.0.0.dist-info/top_level.txt
apimaticcalculatorlatest-4.0.0.dist-info/RECORD
